README.md
setup.py
aio_bitrix/__init__.py
aio_bitrix/exceptions.py
aio_bitrix.egg-info/PKG-INFO
aio_bitrix.egg-info/SOURCES.txt
aio_bitrix.egg-info/dependency_links.txt
aio_bitrix.egg-info/requires.txt
aio_bitrix.egg-info/top_level.txt